kfsfstr/kfsfstr.py
kfsfstr-2.0.0.dist-info/METADATA
kfsfstr-2.0.0.dist-info/WHEEL
kfsfstr-2.0.0.dist-info/RECORD
