Metadata-Version: 2.1
Name: kfsfstr
Version: 2.0.0
Summary: 
Home-page: https://github.com/9-FS/kfsfstr
License: MIT
Author: 9FS
Author-email: pray4spam@googlemail.com
Requires-Python: >=3.12.0,<4.0.0
Classifier: License :: OSI Approved :: MIT License
Classifier: Programming Language :: Python :: 3
Classifier: Programming Language :: Python :: 3.12
Requires-Dist: colorama (>=0.4.0,<0.5.0)
Project-URL: Repository, https://github.com/9-FS/kfsfstr
